LICENSE.txt
MANIFEST.in
README.txt
setup.py
mood/__init__.py
mood.msgpack.egg-info/PKG-INFO
mood.msgpack.egg-info/SOURCES.txt
mood.msgpack.egg-info/dependency_links.txt
mood.msgpack.egg-info/namespace_packages.txt
mood.msgpack.egg-info/not-zip-safe
mood.msgpack.egg-info/top_level.txt
src/msgpack.c
src/helpers/helpers.c