Metadata-Version: 1.2
Name: mood.msgpack
Version: 1.0.0
Summary: Python MessagePack implementation
Home-page: https://github.com/lekma/mood.msgpack
Author: Malek Hadj-Ali
Author-email: lekmalek@gmail.com
License: GNU General Public License v3 (GPLv3)
Download-URL: https://github.com/lekma/mood.msgpack/releases
Project-URL: Bug Tracker, https://github.com/lekma/mood.msgpack/issues
Keywords: messagepack msgpack
Platform: POSIX
Classifier: Development Status :: 5 - Production/Stable
Classifier: Intended Audience :: Developers
Classifier: License :: OSI Approved :: GNU General Public License v3 (GPLv3)
Classifier: Operating System :: POSIX
Classifier: Programming Language :: Python :: 3.5
Classifier: Programming Language :: Python :: Implementation :: CPython
Requires-Python: ~=3.5
